nblab-1.0.2.dist-info/RECORD
nblab-1.0.2.dist-info/WHEEL
nblab-1.0.2.dist-info/METADATA
nblab-1.0.2.dist-info/top_level.txt
NLab/__init__.py
NLab/DataView/run.py
NLab/DataView/log_browser.cpython-38-x86_64-linux-gnu.so
NLab/Manual/view.pdf
NLab/Instruments/Instrument.cpython-38-x86_64-linux-gnu.so
NLab/Base/servers.cpython-38-x86_64-linux-gnu.so
NLab/Base/base_root.cpython-38-x86_64-linux-gnu.so
NLab/Utils/rwjson.cpython-38-x86_64-linux-gnu.so
NLab/Utils/common.cpython-38-x86_64-linux-gnu.so
NLab/Utils/pltr.cpython-38-x86_64-linux-gnu.so
NLab/Utils/rwdata.cpython-38-x86_64-linux-gnu.so
NLab/Utils/loadcsv.cpython-38-x86_64-linux-gnu.so
NLab/Utils/tracer.cpython-38-x86_64-linux-gnu.so
NLab/Utils/multiploter/adj.cpython-38-x86_64-linux-gnu.so
NLab/Utils/multiploter/conf.cpython-38-x86_64-linux-gnu.so
NLab/Utils/multiploter/ploter.cpython-38-x86_64-linux-gnu.so
NLab/Utils/multiploter/ds.cpython-38-x86_64-linux-gnu.so
NLab/Utils/multiploter/mulpltr.cpython-38-x86_64-linux-gnu.so
NLab/Utils/multiploter/que.cpython-38-x86_64-linux-gnu.so
